LICENSE
MANIFEST.in
README.md
setup.cfg
setup.py
django_likeit.egg-info/PKG-INFO
django_likeit.egg-info/SOURCES.txt
django_likeit.egg-info/dependency_links.txt
django_likeit.egg-info/top_level.txt
like/__init__.py
like/admin.py
like/managers.py
like/models.py
like/urls.py
like/views.py
like/static/like.js
like/templates/like/button.html
like/templatetags/__init__.py
like/templatetags/like_tags.py