Metadata-Version: 1.1
Name: django-likeit
Version: 0.1.1
Summary: It's developed on Python 3.5 & Python 3.6 for Django 1.10 and later.
Home-page: https://github.com/malisit/django-likeit
Author: Muhammed Ali Sit
Author-email: sitmuhammedali@gmail.com
License: MIT License
Download-URL: https://github.com/malisit/django-likeit/tarball/0.1
Platform: UNKNOWN
Classifier: Environment :: Web Environment
Classifier: Framework :: Django
Classifier: Intended Audience :: Developers
Classifier: License :: OSI Approved :: MIT License
Classifier: Operating System :: OS Independent
Classifier: Programming Language :: Python
Classifier: Programming Language :: Python :: 3.5
Classifier: Programming Language :: Python :: 3.6
Classifier: Topic :: Internet :: WWW/HTTP
Classifier: Topic :: Internet :: WWW/HTTP :: Dynamic Content
